Metadata-Version: 2.1
Name: groundingdino-py
Version: 0.1.0
Summary: open-set object detector
Home-page: https://github.com/IDEA-Research/GroundingDINO
Author: International Digital Economy Academy, Shilong Liu
License:                                  Apache License
License-File: LICENSE
